currency/__init__.py
currency/converter.py
currency_converter_rate-1.0.4.dist-info/METADATA
currency_converter_rate-1.0.4.dist-info/WHEEL
currency_converter_rate-1.0.4.dist-info/top_level.txt
currency_converter_rate-1.0.4.dist-info/RECORD
