Metadata-Version: 2.1
Name: currency-converter-rate
Version: 1.0.4
Summary: Currency Converter Rate
Home-page: https://github.com/SameerShiekh77/Currency-Conversion-Python-Package
Author: Muhammad Sameer
Author-email: muhammadsameer.css@gmail.com
License: UNKNOWN
Keywords: python,conversion,currency conversion,rate,curency rate package
Platform: UNKNOWN
Classifier: Development Status :: 1 - Planning
Classifier: Intended Audience :: Developers
Classifier: Programming Language :: Python :: 3
Classifier: Operating System :: Unix
Classifier: Operating System :: MacOS :: MacOS X
Classifier: Operating System :: Microsoft :: Windows
Requires-Python: >=3.6
Requires-Dist: cachetools
Requires-Dist: requests
